myproject/__init__.py
myproject/hello.py
myproject/version.py
python_test_setup-0.14.dist-info/METADATA
python_test_setup-0.14.dist-info/RECORD
python_test_setup-0.14.dist-info/WHEEL
python_test_setup-0.14.dist-info/top_level.txt
